trajpy/__init__.py
trajpy/auxiliar_functions.py
trajpy/logo.png
trajpy/traj_generator.py
trajpy/trajpy.py
trajpy-1.4.4.dist-info/METADATA
trajpy-1.4.4.dist-info/WHEEL
trajpy-1.4.4.dist-info/licenses/LICENSE
trajpy-1.4.4.dist-info/RECORD
