Metadata-Version: 2.4
Name: trajpy
Version: 1.4.4
Summary: Trajpy - empowering feature engineering for trajectory analysis across domains.
License-Expression: MIT
License-File: LICENSE
Keywords: python,trajectory,time-series,repeated-mesurements
Author: Maurício Moreira Soares
Author-email: trajpy@protonmail.ch
Requires-Python: >=3.11,<4.0
Classifier: Programming Language :: Python :: 3
Classifier: Programming Language :: Python :: 3.11
Classifier: Programming Language :: Python :: 3.12
Classifier: Programming Language :: Python :: 3.13
Classifier: Programming Language :: Python :: 3.14
Provides-Extra: docs
Requires-Dist: PyYAML (>=5.3.1)
Requires-Dist: nbsphinx (>=0.9.0) ; extra == "docs"
Requires-Dist: numpy (>=1.14.3)
Requires-Dist: scipy (>=1.7.1)
Requires-Dist: sphinx (>=7.0.0) ; extra == "docs"
Requires-Dist: sphinx-autodoc-typehints (>=1.25.0) ; extra == "docs"
Requires-Dist: sphinx-rtd-theme (>=2.0.0) ; extra == "docs"
Project-URL: Homepage, https://github.com/ocbe-uio/trajpy
